mazex/__init__.py
mazex/mazex.py
mazex-1.0.0.dist-info/LICENSE
mazex-1.0.0.dist-info/METADATA
mazex-1.0.0.dist-info/WHEEL
mazex-1.0.0.dist-info/dependency_links.txt
mazex-1.0.0.dist-info/entry_points.txt
mazex-1.0.0.dist-info/top_level.txt
mazex-1.0.0.dist-info/RECORD
