Metadata-Version: 2.1
Name: mazex
Version: 1.0.0
Summary: mazex is a simple game under the terminal where you have to find the way to the goal in the maze with the most optimal path and solve the challenges.
Home-page: https://github.com/mimseyedi/mazex
Author: mimseyedi
Author-email: mim.seyedi@gmail.com
License: MIT
Classifier: License :: OSI Approved :: MIT License
Classifier: Programming Language :: Python :: 3
Classifier: Programming Language :: Python :: 3.6
Classifier: Programming Language :: Python :: 3.8
Requires-Python: >=3.6
License-File: LICENSE
Requires-Dist: click
